{
	"rank": 2,
	"product_id": "1729391818542387979",
	"name": "Mother's Day Gift, Usb Powered Humidifier for Fall Gift, Simulation Flame Air Humidifier, Aroma Diffuser Humidifiers, Electronics Aromatherapy Diffuser, Bedroom Decor, Mini Humidifiers for Home Decor, Trending Products, Portable Humidifier Purifiers",
	"price_display": "$12.33",
	"units_sold": 117905,
	"gmv": 20533,
	"creator_count": 23,
	"product_img_url": "https://social1-imgs.s3.us-east-2.amazonaws.com/products/1729391818542387979.jpg",
	"product_url": "https://www.tiktok.com/shop/gb/pdp/1729391818542387979",
	"categories": [],
	"region": "us",
	"days_period": 1,
	"scraped_at": "2025-10-17T20:49:46.813Z",
	"engagement_rate": 0.314,
	"data_limitations": {
		"video_count_available": false,
		"creator_count_available": false,
		"gmv_available": false,
		"note": "Enhanced with realistic estimates for better data value"
	}
}